pyfnz/__init__.py
pyfnz/clj.py
pyfnz/either.py
pyfnz/tri.py
pyfnz-0.1.2.dist-info/LICENSE.txt
pyfnz-0.1.2.dist-info/METADATA
pyfnz-0.1.2.dist-info/WHEEL
pyfnz-0.1.2.dist-info/top_level.txt
pyfnz-0.1.2.dist-info/RECORD
