Metadata-Version: 2.1
Name: pyfnz
Version: 0.1.2
Summary: Pythonic Functional Constructs
Home-page: https://github.com/papaver/pyfnz
Author: Moiz Merchant
Author-email: moiz@electronicdreams.io
License: BSD 3-Clause License
Platform: UNKNOWN
Classifier: Intended Audience :: Developers
Classifier: License :: OSI Approved :: BSD License
Classifier: Programming Language :: Python :: 2.7
Classifier: Programming Language :: Python :: 3.7
